package/__init__.py
package/main.py
outlier_detector_vvgu-1.0.0.dist-info/LICENSE
outlier_detector_vvgu-1.0.0.dist-info/METADATA
outlier_detector_vvgu-1.0.0.dist-info/WHEEL
outlier_detector_vvgu-1.0.0.dist-info/top_level.txt
outlier_detector_vvgu-1.0.0.dist-info/RECORD
