Metadata-Version: 2.1
Name: outlier-detector-vvgu
Version: 1.0.0
Summary: Small package for detecting outliers
Home-page: https://github.com/Artorius81
Author: Artorius
Author-email: Artorius.81@yandex.ru
Project-URL: GitHub, https://github.com/Artorius81
Keywords: example python
Classifier: Programming Language :: Python :: 3.11
Classifier: License :: OSI Approved :: MIT License
Classifier: Operating System :: OS Independent
Requires-Python: >=3.7
License-File: LICENSE
Requires-Dist: requests (>=2.25.1)
